{
  "time": "2026/7/11 21:19:33",
  "data": [
    {
      "server": "太陽神阿波羅",
      "buy": "2.2179",
      "sell": "2.1519"
    },
    {
      "server": "收獲女神蒂蜜特",
      "buy": "1.6860",
      "sell": "1.6483"
    },
    {
      "server": "勝利女神雅典娜",
      "buy": "1.8382",
      "sell": "1.8096"
    },
    {
      "server": "戰神馬爾斯",
      "buy": "1.3500",
      "sell": "1.3535"
    },
    {
      "server": "泰坦女神瑞亞",
      "buy": "1.2749",
      "sell": "1.2488"
    },
    {
      "server": "水蛇許德拉",
      "buy": "1.9000",
      "sell": "1.6675"
    },
    {
      "server": "蛇髮女墨杜沙",
      "buy": "1.5556",
      "sell": "1.5154"
    },
    {
      "server": "美神維納斯",
      "buy": "1.4747",
      "sell": "1.4351"
    },
    {
      "server": "月亮女神阿緹蜜斯",
      "buy": "1.5000",
      "sell": "1.4304"
    },
    {
      "server": "冥王黑帝斯",
      "buy": "1.5500",
      "sell": "1.4292"
    },
    {
      "server": "半人馬涅索斯",
      "buy": "1.8055",
      "sell": "1.7621"
    },
    {
      "server": "天神宙斯",
      "buy": "2.2279",
      "sell": "2.1882"
    },
    {
      "server": "海神波塞頓",
      "buy": "2.0379",
      "sell": "1.9055"
    },
    {
      "server": "火神赫發斯特斯",
      "buy": "2.4462",
      "sell": "2.3883"
    },
    {
      "server": "愛神邱比特",
      "buy": "1.9332",
      "sell": "1.8228"
    },
    {
      "server": "天后海拉",
      "buy": "1.9540",
      "sell": "1.9301"
    },
    {
      "server": "牛人彌諾陶洛斯",
      "buy": "1.6589",
      "sell": "1.6589"
    }
  ]
}