{
  "time": "2026/6/10 18:01:37",
  "data": [
    {
      "server": "太陽神阿波羅",
      "buy": "2.7983",
      "sell": "2.7488"
    },
    {
      "server": "收獲女神蒂蜜特",
      "buy": "2.1971",
      "sell": "2.1978"
    },
    {
      "server": "勝利女神雅典娜",
      "buy": "2.7400",
      "sell": "2.7181"
    },
    {
      "server": "戰神馬爾斯",
      "buy": "2.1400",
      "sell": "2.1008"
    },
    {
      "server": "泰坦女神瑞亞",
      "buy": "1.7400",
      "sell": "1.6077"
    },
    {
      "server": "水蛇許德拉",
      "buy": "2.3000",
      "sell": "2.2331"
    },
    {
      "server": "蛇髮女墨杜沙",
      "buy": "2.2200",
      "sell": "2.1796"
    },
    {
      "server": "美神維納斯",
      "buy": "2.4290",
      "sell": "2.4038"
    },
    {
      "server": "月亮女神阿緹蜜斯",
      "buy": "2.7000",
      "sell": "2.6774"
    },
    {
      "server": "冥王黑帝斯",
      "buy": "2.2684",
      "sell": "2.2326"
    },
    {
      "server": "半人馬涅索斯",
      "buy": "2.4928",
      "sell": "2.3485"
    },
    {
      "server": "天神宙斯",
      "buy": "2.8301",
      "sell": "2.8066"
    },
    {
      "server": "海神波塞頓",
      "buy": "2.3900",
      "sell": "2.4155"
    },
    {
      "server": "火神赫發斯特斯",
      "buy": "2.6364",
      "sell": "2.5589"
    },
    {
      "server": "愛神邱比特",
      "buy": "2.0889",
      "sell": "2.0178"
    },
    {
      "server": "天后海拉",
      "buy": "3.4380",
      "sell": "3.4014"
    },
    {
      "server": "牛人彌諾陶洛斯",
      "buy": "1.8600",
      "sell": "1.8139"
    }
  ]
}