{
  "time": "2026/7/8 15:29:00",
  "data": [
    {
      "server": "太陽神阿波羅",
      "buy": "1.7945",
      "sell": "1.7581"
    },
    {
      "server": "收獲女神蒂蜜特",
      "buy": "1.4700",
      "sell": "1.4468"
    },
    {
      "server": "勝利女神雅典娜",
      "buy": "1.5900",
      "sell": "1.5286"
    },
    {
      "server": "戰神馬爾斯",
      "buy": "1.3956",
      "sell": "1.3233"
    },
    {
      "server": "泰坦女神瑞亞",
      "buy": "1.2280",
      "sell": "1.1208"
    },
    {
      "server": "水蛇許德拉",
      "buy": "1.5488",
      "sell": "1.4548"
    },
    {
      "server": "蛇髮女墨杜沙",
      "buy": "1.3093",
      "sell": "1.2740"
    },
    {
      "server": "美神維納斯",
      "buy": "1.3913",
      "sell": "1.3247"
    },
    {
      "server": "月亮女神阿緹蜜斯",
      "buy": "1.3988",
      "sell": "1.3444"
    },
    {
      "server": "冥王黑帝斯",
      "buy": "1.3700",
      "sell": "1.4599"
    },
    {
      "server": "半人馬涅索斯",
      "buy": "1.5749",
      "sell": "1.4422"
    },
    {
      "server": "天神宙斯",
      "buy": "1.9000",
      "sell": "1.7612"
    },
    {
      "server": "海神波塞頓",
      "buy": "1.5800",
      "sell": "1.5647"
    },
    {
      "server": "火神赫發斯特斯",
      "buy": "1.9497",
      "sell": "1.7781"
    },
    {
      "server": "愛神邱比特",
      "buy": "1.4882",
      "sell": "1.4611"
    },
    {
      "server": "天后海拉",
      "buy": "1.5498",
      "sell": "1.5108"
    },
    {
      "server": "牛人彌諾陶洛斯",
      "buy": "1.4750",
      "sell": "1.3278"
    }
  ]
}