{
  "time": "2026/6/10 21:35:10",
  "data": [
    {
      "server": "太陽神阿波羅",
      "buy": "2.7700",
      "sell": "2.7473"
    },
    {
      "server": "收獲女神蒂蜜特",
      "buy": "2.1000",
      "sell": "2.1231"
    },
    {
      "server": "勝利女神雅典娜",
      "buy": "2.7624",
      "sell": "2.7624"
    },
    {
      "server": "戰神馬爾斯",
      "buy": "2.2450",
      "sell": "2.1436"
    },
    {
      "server": "泰坦女神瑞亞",
      "buy": "1.7150",
      "sell": "1.7001"
    },
    {
      "server": "水蛇許德拉",
      "buy": "2.3436",
      "sell": "2.2738"
    },
    {
      "server": "蛇髮女墨杜沙",
      "buy": "2.2502",
      "sell": "2.2070"
    },
    {
      "server": "美神維納斯",
      "buy": "2.4000",
      "sell": "2.3923"
    },
    {
      "server": "月亮女神阿緹蜜斯",
      "buy": "2.6759",
      "sell": "2.5913"
    },
    {
      "server": "冥王黑帝斯",
      "buy": "2.3100",
      "sell": "2.2502"
    },
    {
      "server": "半人馬涅索斯",
      "buy": "2.3763",
      "sell": "2.3326"
    },
    {
      "server": "天神宙斯",
      "buy": "2.8000",
      "sell": "2.7586"
    },
    {
      "server": "海神波塞頓",
      "buy": "2.3300",
      "sell": "2.3697"
    },
    {
      "server": "火神赫發斯特斯",
      "buy": "2.6100",
      "sell": "2.5575"
    },
    {
      "server": "愛神邱比特",
      "buy": "2.1786",
      "sell": "2.1013"
    },
    {
      "server": "天后海拉",
      "buy": "3.4090",
      "sell": "3.3681"
    },
    {
      "server": "牛人彌諾陶洛斯",
      "buy": "1.7891",
      "sell": "1.7473"
    }
  ]
}