{
  "time": "2026/6/4 00:50:10",
  "data": [
    {
      "server": "太陽神阿波羅",
      "buy": "2.7647",
      "sell": "2.7397"
    },
    {
      "server": "收獲女神蒂蜜特",
      "buy": "2.5395",
      "sell": "2.5310"
    },
    {
      "server": "勝利女神雅典娜",
      "buy": "2.6892",
      "sell": "2.6462"
    },
    {
      "server": "戰神馬爾斯",
      "buy": "2.3300",
      "sell": "2.2548"
    },
    {
      "server": "泰坦女神瑞亞",
      "buy": "2.2096",
      "sell": "2.1368"
    },
    {
      "server": "水蛇許德拉",
      "buy": "2.3900",
      "sell": "2.3496"
    },
    {
      "server": "蛇髮女墨杜沙",
      "buy": "2.4300",
      "sell": "2.3590"
    },
    {
      "server": "美神維納斯",
      "buy": "2.5500",
      "sell": "2.5648"
    },
    {
      "server": "月亮女神阿緹蜜斯",
      "buy": "2.8500",
      "sell": "2.9061"
    },
    {
      "server": "冥王黑帝斯",
      "buy": "2.3800",
      "sell": "2.3277"
    },
    {
      "server": "半人馬涅索斯",
      "buy": "2.5300",
      "sell": "2.4839"
    },
    {
      "server": "天神宙斯",
      "buy": "2.8605",
      "sell": "2.8910"
    },
    {
      "server": "海神波塞頓",
      "buy": "2.8352",
      "sell": "2.8098"
    },
    {
      "server": "火神赫發斯特斯",
      "buy": "2.7900",
      "sell": "2.7322"
    },
    {
      "server": "愛神邱比特",
      "buy": "2.5199",
      "sell": "2.4242"
    },
    {
      "server": "天后海拉",
      "buy": "3.6000",
      "sell": "3.5714"
    },
    {
      "server": "牛人彌諾陶洛斯",
      "buy": "2.2297",
      "sell": "2.1887"
    }
  ]
}