{
  "time": "2026/6/6 19:40:34",
  "data": [
    {
      "server": "太陽神阿波羅",
      "buy": "2.8889",
      "sell": "2.8369"
    },
    {
      "server": "收獲女神蒂蜜特",
      "buy": "2.5383",
      "sell": "2.5202"
    },
    {
      "server": "勝利女神雅典娜",
      "buy": "2.7448",
      "sell": "2.7034"
    },
    {
      "server": "戰神馬爾斯",
      "buy": "2.3499",
      "sell": "2.2563"
    },
    {
      "server": "泰坦女神瑞亞",
      "buy": "2.1313",
      "sell": "2.0674"
    },
    {
      "server": "水蛇許德拉",
      "buy": "2.4500",
      "sell": "2.4073"
    },
    {
      "server": "蛇髮女墨杜沙",
      "buy": "2.3332",
      "sell": "2.2594"
    },
    {
      "server": "美神維納斯",
      "buy": "2.6000",
      "sell": "2.6110"
    },
    {
      "server": "月亮女神阿緹蜜斯",
      "buy": "2.7500",
      "sell": "2.8257"
    },
    {
      "server": "冥王黑帝斯",
      "buy": "2.3699",
      "sell": "2.3283"
    },
    {
      "server": "半人馬涅索斯",
      "buy": "2.5389",
      "sell": "2.5202"
    },
    {
      "server": "天神宙斯",
      "buy": "2.9190",
      "sell": "2.8629"
    },
    {
      "server": "海神波塞頓",
      "buy": "2.8100",
      "sell": "2.8177"
    },
    {
      "server": "火神赫發斯特斯",
      "buy": "2.8500",
      "sell": "2.7548"
    },
    {
      "server": "愛神邱比特",
      "buy": "2.5472",
      "sell": "2.4564"
    },
    {
      "server": "天后海拉",
      "buy": "3.4999",
      "sell": "3.4965"
    },
    {
      "server": "牛人彌諾陶洛斯",
      "buy": "2.1429",
      "sell": "2.1017"
    }
  ]
}